pg_db_migrator/__init__.py
pg_db_migrator/migrator.py
pg_db_migrator/schema_resolve.py
pg_db_migrator-0.1.1.dist-info/METADATA
pg_db_migrator-0.1.1.dist-info/RECORD
pg_db_migrator-0.1.1.dist-info/WHEEL
pg_db_migrator-0.1.1.dist-info/top_level.txt
