Metadata-Version: 2.1
Name: pg-db-migrator
Version: 0.1.1
Summary: UNKNOWN
Home-page: UNKNOWN
Author: Ziyang Hu
Author-email: hu.ziyang@cantab.net
License: UNKNOWN
Platform: UNKNOWN
Requires-Dist: psycopg2-binary
Requires-Dist: tarjan
